django_stimulus/__init__.py
django_stimulus-0.2.0.dist-info/METADATA
django_stimulus-0.2.0.dist-info/WHEEL
django_stimulus-0.2.0.dist-info/RECORD
